pyeffects/Either.py
pyeffects/Future.py
pyeffects/Monad.py
pyeffects/Option.py
pyeffects/Try.py
pyeffects/__init__.py
pyeffects/__version__.py
pyeffects-1.0.5.dist-info/LICENSE
pyeffects-1.0.5.dist-info/METADATA
pyeffects-1.0.5.dist-info/WHEEL
pyeffects-1.0.5.dist-info/top_level.txt
pyeffects-1.0.5.dist-info/RECORD
