Metadata-Version: 2.1
Name: pyeffects
Version: 1.0.5
Summary: Monads for Python.  Side-effect explicitly.
Home-page: https://github.com/vickumar1981/pyeffects
Author: Vic Kumar
Author-email: vickumar@gmail.com
License: Apache 2.0
Project-URL: Source, https://github.com/vickumar1981/pyeffects
Platform: UNKNOWN
Classifier: Development Status :: 5 - Production/Stable
Classifier: Intended Audience :: Developers
Classifier: Natural Language :: English
Classifier: License :: OSI Approved :: Apache Software License
Classifier: Programming Language :: Python
Classifier: Programming Language :: Python :: 2
Classifier: Programming Language :: Python :: 2.7
Classifier: Programming Language :: Python :: 3
Classifier: Programming Language :: Python :: 3.5
Classifier: Programming Language :: Python :: 3.6
Classifier: Programming Language :: Python :: 3.7
Classifier: Programming Language :: Python :: 3.8
Classifier: Programming Language :: Python :: Implementation :: CPython
Classifier: Programming Language :: Python :: Implementation :: PyPy
Requires-Python: >=3.6
License-File: LICENSE
